desdemona/__init__.py
desdemona/games.py
desdemona/messages.py
desdemona/othello.py
desdemona/perft.py
desdemona/player.py
desdemona/server.py
desdemona/static/style.css
desdemona/templates/base.html
desdemona/templates/home.html
desdemona/templates/view.html
desdemona-0.1.4.dist-info/entry_points.txt
desdemona-0.1.4.dist-info/WHEEL
desdemona-0.1.4.dist-info/METADATA
desdemona-0.1.4.dist-info/RECORD
