Metadata-Version: 2.1
Name: desdemona
Version: 0.1.4
Summary: A server for othello AI games
Author: Brian Cruz
Author-email: cruz.s.brian@gmail.com
Requires-Python: >=3.6,<4.0
Classifier: Programming Language :: Python :: 3
Classifier: Programming Language :: Python :: 3.6
Classifier: Programming Language :: Python :: 3.7
Classifier: Programming Language :: Python :: 3.8
Classifier: Programming Language :: Python :: 3.9
Requires-Dist: Flask (>=1.1.2,<2.0.0)
Requires-Dist: Flask-SocketIO (>=5.0.1,<6.0.0)
Requires-Dist: coolname (>=1.1.0,<2.0.0)
Requires-Dist: dataclasses-json (>=0.5.2,<0.6.0)
Requires-Dist: eventlet (>=0.30.2,<0.31.0)
Requires-Dist: numpy (>=1.19.1,<2.0.0)
Requires-Dist: python-socketio[client] (>=5.0.4,<6.0.0)
